LICENSE
MANIFEST.in
README.md
requirements.txt
setup.py
django_saml2_idp.egg-info/PKG-INFO
django_saml2_idp.egg-info/SOURCES.txt
django_saml2_idp.egg-info/dependency_links.txt
django_saml2_idp.egg-info/requires.txt
django_saml2_idp.egg-info/top_level.txt
saml2idp/__init__.py
saml2idp/base.py
saml2idp/codex.py
saml2idp/exceptions.py
saml2idp/google_apps.py
saml2idp/metadata.py
saml2idp/models.py
saml2idp/registry.py
saml2idp/salesforce.py
saml2idp/saml2idp_metadata.py
saml2idp/urls.py
saml2idp/views.py
saml2idp/xml_render.py
saml2idp/xml_signing.py
saml2idp/xml_templates.py
saml2idp/templates/saml2idp/base.html
saml2idp/templates/saml2idp/idpssodescriptor.xml
saml2idp/templates/saml2idp/invalid_user.html
saml2idp/templates/saml2idp/logged_out.html
saml2idp/templates/saml2idp/login.html
saml2idp/tests/__init__.py
saml2idp/tests/__init__.pyc
saml2idp/tests/base.py
saml2idp/tests/base.pyc
saml2idp/tests/deeplink.py
saml2idp/tests/deeplink.pyc
saml2idp/tests/google_apps.py
saml2idp/tests/salesforce.py
saml2idp/tests/signing.py
saml2idp/tests/views.py