Metadata-Version: 1.0
Name: django-saml2-idp
Version: 0.1
Summary: ('SAML 2.0 IdP for Django',)
Home-page: https://github.com/abhinavsingh/django-saml2
Author: John Samuel Anderson
Author-email: john@andersoninnovative.com
License: MIT
Platform: UNKNOWN
